s3_analyst/__init__.py
s3_analyst/cli.py
s3_analyst/s3_analyst.py
s3_analyst/s3_analyst_logging.py
s3_analyst-0.3.2.data/scripts/coveos3tool
s3_analyst-0.3.2.dist-info/DESCRIPTION.rst
s3_analyst-0.3.2.dist-info/METADATA
s3_analyst-0.3.2.dist-info/RECORD
s3_analyst-0.3.2.dist-info/WHEEL
s3_analyst-0.3.2.dist-info/metadata.json
s3_analyst-0.3.2.dist-info/top_level.txt
