Metadata-Version: 2.0
Name: s3-analyst
Version: 0.3.2
Summary: An AWS S3 storage analysis tool.
Home-page: https://github.com/tofull/devops-coding-challenge
Author: Loïc Messal
Author-email: loic.messal@orange.fr
License: GNU General Public License v3
Keywords: s3_analyst
Platform: UNKNOWN
Classifier: Development Status :: 2 - Pre-Alpha
Classifier: Intended Audience :: Developers
Classifier: License :: OSI Approved :: GNU General Public License v3 (GPLv3)
Classifier: Natural Language :: English
Classifier: Programming Language :: Python :: 3
Classifier: Programming Language :: Python :: 3.5
Requires-Dist: PyYAML (==3.12)
Requires-Dist: boto3 (==1.4.7)
Requires-Dist: cryptography (==2.0.3)
Requires-Dist: docopt (==0.6.2)
Requires-Dist: docutils (==0.12)
Requires-Dist: pandas (==0.20.3)
Requires-Dist: schema (==0.6.6)
